{"ProductName": "幻境PRO", "DisplayName": "幻境PRO - 22 LED", "Brand": "CompGen", "Type": "custom", "LedCount": 22, "Width": 11, "Height": 11, "LedMapping": [0, 1, 2, 3, 4, 5, 6, 7, 8, 9, 10, 11, 12, 13, 14, 15, 16, 17, 18, 19, 20, 21], "LedCoordinates": [[9, 2], [10, 3], [10, 4], [10, 5], [10, 6], [10, 7], [9, 8], [8, 9], [6, 10], [4, 10], [2, 9], [1, 8], [0, 7], [0, 6], [0, 5], [0, 4], [0, 3], [1, 2], [2, 1], [4, 0], [6, 0], [8, 1]], "LedNames": ["Led1", "Led2", "Led3", "Led4", "Led5", "Led6", "Led7", "Led8", "Led9", "Led10", "Led11", "Led12", "Led13", "Led14", "Led15", "Led16", "Led17", "Led18", "Led19", "Led20", "Led21", "Led22"], "ImageUrl":"https://gitee.com/drgb-controller/drgb/raw/master/Image/Universal%20fan.png"
}